SFOF4S/__init__.py
SFOF4S/model/__init__.py
SFOF4S/model/edge_superres_pytorch.py
SFOF4S/model/edge_superres_tensorflow.py
SFOF4S/model/opencv_functions.py
SFOF4S/processor/__init__.py
SFOF4S/processor/angle_detection.py
SFOF4S/processor/baseline_detection.py
SFOF4S/processor/criteria_definition.py
SFOF4S/processor/main.py
SFOF4S/processor/tools.py
SFOF4S/processor/visualization.py
SFOF4S/utils/__init__.py
SFOF4S-1.0.13.dist-info/LICENSE
SFOF4S-1.0.13.dist-info/METADATA
SFOF4S-1.0.13.dist-info/WHEEL
SFOF4S-1.0.13.dist-info/top_level.txt
SFOF4S-1.0.13.dist-info/RECORD
