Metadata-Version: 2.2
Name: SFOF4S
Version: 1.0.13
Summary: This toolkit aids in analyzing drop sliding on tilted plates, allowing researchers to study various variables and their correlations in detail.
Home-page: https://github.com/yriyazi/SFOF4S
Author: Sajjad Shumaly
Maintainer: Yassin Riyazi
Maintainer-email: iyasiniyasin98@gmail.com
Project-URL: Source Code, https://github.com/AK-Berger/4S-SROF
Project-URL: documentation, https://github.com/yriyazi/SFOF4S-Documentation
Keywords: machine learning,computer vision,PyTorch,SciPy,OpenCV,droplet,contact angle
Classifier: Programming Language :: Python :: 3
Classifier: License :: OSI Approved :: MIT License
Classifier: Operating System :: OS Independent
Requires-Python: >=3.12
License-File: LICENSE
Requires-Dist: torch>=2.6
Requires-Dist: torchaudio>=2.4
Requires-Dist: torchvision>=0.21
Requires-Dist: numpy>=1.26
Requires-Dist: opencv-python>=4.10
Requires-Dist: scipy>=1.15
Requires-Dist: tqdm>=4.67
Requires-Dist: pandas>=2.2
Requires-Dist: natsort>=8.4
Requires-Dist: requests>=2.32
Requires-Dist: matplotlib>=3.9
Dynamic: author
Dynamic: classifier
Dynamic: description
Dynamic: description-content-type
Dynamic: home-page
Dynamic: keywords
Dynamic: maintainer
Dynamic: maintainer-email
Dynamic: project-url
Dynamic: requires-dist
Dynamic: requires-python
Dynamic: summary
